{
    "camera_stage_mapping_calibration": {
        "backlash": 0.0,
        "backlash_vector": [
            0.0,
            0.0,
            0.0
        ],
        "image_to_stage_displacement": [
            [
                -0.0012067713953994147,
                1.0026877733034147
            ],
            [
                -1.0026877733034136,
                0.0012067713954004155
            ]
        ]
    },
    "linear_calibration_X": {
        "backlash": 0,
        "backlash_corrected_moves": [
            [
                [
                    -256.0,
                    -358.40000000000003,
                    0.0
                ]
            ],
            [
                [
                    -358.0,
                    256.0
                ]
            ],
            [
                1715723880.422456
            ]
        ],
        "exponential_moves": [
            [
                [
                    -0.0,
                    -0.0,
                    0.0
                ],
                [
                    -1.0,
                    -0.0,
                    0.0
                ],
                [
                    -2.0,
                    -0.0,
                    0.0
                ],
                [
                    -4.0,
                    -0.0,
                    0.0
                ],
                [
                    -8.0,
                    -0.0,
                    0.0
                ],
                [
                    -16.0,
                    -0.0,
                    0.0
                ],
                [
                    -32.0,
                    -0.0,
                    0.0
                ],
                [
                    -64.0,
                    -0.0,
                    0.0
                ],
                [
                    -128.0,
                    -0.0,
                    0.0
                ],
                [
                    -0.0,
                    128.0,
                    0.0
                ],
                [
                    -64.0,
                    128.0,
                    0.0
                ],
                [
                    -128.0,
                    128.0,
                    0.0
                ],
                [
                    -192.0,
                    128.0,
                    0.0
                ],
                [
                    -256.0,
                    128.0,
                    0.0
                ],
                [
                    -320.0,
                    128.0,
                    0.0
                ],
                [
                    -384.0,
                    128.0,
                    0.0
                ]
            ],
            [
                [
                    0.0,
                    0.0
                ],
                [
                    0.0,
                    1.0
                ],
                [
                    0.0,
                    2.0
                ],
                [
                    0.0,
                    4.0
                ],
                [
                    0.0,
                    8.0
                ],
                [
                    0.0,
                    16.0
                ],
                [
                    0.0,
                    32.0
                ],
                [
                    0.0,
                    64.0
                ],
                [
                    0.0,
                    128.0
                ],
                [
                    128.0,
                    0.0
                ],
                [
                    128.0,
                    64.0
                ],
                [
                    128.0,
                    128.0
                ],
                [
                    128.0,
                    192.0
                ],
                [
                    128.0,
                    256.0
                ],
                [
                    128.0,
                    320.0
                ],
                [
                    128.0,
                    384.0
                ]
            ],
            [
                1715723864.527074,
                1715723865.008323,
                1715723865.553854,
                1715723866.063633,
                1715723866.587208,
                1715723867.105815,
                1715723867.8324878,
                1715723868.3376482,
                1715723868.8525262,
                1715723869.367618,
                1715723869.884272,
                1715723870.476053,
                1715723871.005228,
                1715723871.537075,
                1715723872.0494452,
                1715723872.635464
            ]
        ],
        "fractional_error": 0.0004374971801513096,
        "image_direction": [
            0.6390412089483677,
            -0.7691724990311398
        ],
        "linear_moves": [
            [
                [
                    0.0,
                    0.0,
                    0.0
                ],
                [
                    51.2,
                    -0.0,
                    0.0
                ],
                [
                    102.4,
                    -0.0,
                    0.0
                ],
                [
                    153.60000000000002,
                    -0.0,
                    0.0
                ],
                [
                    204.8,
                    -0.0,
                    0.0
                ],
                [
                    256.0,
                    -0.0,
                    0.0
                ],
                [
                    307.20000000000005,
                    -0.0,
                    0.0
                ],
                [
                    358.40000000000003,
                    -0.0,
                    0.0
                ],
                [
                    358.40000000000003,
                    -0.0,
                    0.0
                ],
                [
                    -51.2,
                    -358.40000000000003,
                    0.0
                ],
                [
                    -102.4,
                    -358.40000000000003,
                    0.0
                ],
                [
                    -153.60000000000002,
                    -358.40000000000003,
                    0.0
                ],
                [
                    -204.8,
                    -358.40000000000003,
                    0.0
                ],
                [
                    -256.0,
                    -358.40000000000003,
                    0.0
                ]
            ],
            [
                [
                    0.0,
                    0.0
                ],
                [
                    0.0,
                    -51.0
                ],
                [
                    0.0,
                    -102.00000000000001
                ],
                [
                    0.0,
                    -153.0
                ],
                [
                    0.0,
                    -204.0
                ],
                [
                    0.0,
                    -256.0
                ],
                [
                    0.0,
                    -307.0
                ],
                [
                    0.0,
                    -358.0
                ],
                [
                    0.0,
                    -358.0
                ],
                [
                    -358.0,
                    51.0
                ],
                [
                    -358.0,
                    102.0
                ],
                [
                    -358.0,
                    153.0
                ],
                [
                    -358.0,
                    204.0
                ],
                [
                    -358.0,
                    256.0
                ]
            ],
            [
                1715723873.248254,
                1715723873.7691588,
                1715723874.290003,
                1715723874.8206332,
                1715723875.340641,
                1715723875.923271,
                1715723876.448168,
                1715723876.9739919,
                1715723877.370603,
                1715723877.892815,
                1715723878.3902662,
                1715723878.975842,
                1715723879.501354,
                1715723880.033621
            ]
        ],
        "move_history": [
            [
                1715723864.527543,
                1715723864.653745,
                1715723865.036296,
                1715723865.178386,
                1715723865.564021,
                1715723865.689775,
                1715723866.074219,
                1715723866.2023191,
                1715723866.597901,
                1715723866.7264059,
                1715723867.23633,
                1715723867.39997,
                1715723867.842456,
                1715723867.9672792,
                1715723868.35254,
                1715723868.479254,
                1715723868.8635762,
                1715723868.992901,
                1715723869.377415,
                1715723869.5062258,
                1715723869.8946319,
                1715723870.0267038,
                1715723870.487832,
                1715723870.6200619,
                1715723871.016361,
                1715723871.1437209,
                1715723871.547387,
                1715723871.677886,
                1715723872.059446,
                1715723872.184811,
                1715723872.647733,
                1715723872.819487,
                1715723873.2483761,
                1715723873.418144,
                1715723873.76945,
                1715723873.898536,
                1715723874.2905338,
                1715723874.4190662,
                1715723874.821171,
                1715723874.948956,
                1715723875.3409228,
                1715723875.511334,
                1715723875.9238012,
                1715723876.049066,
                1715723876.4489222,
                1715723876.5725892,
                1715723877.37081,
                1715723877.498219,
                1715723877.8933382,
                1715723878.019897,
                1715723878.390561,
                1715723878.534396,
                1715723878.976577,
                1715723879.127481,
                1715723879.501672,
                1715723879.637919,
                1715723880.422652,
                1715723880.5474,
                1715723880.547402,
                1715723880.684625
            ],
            [
                [
                    -0.0,
                    -0.0,
                    0.0
                ],
                [
                    0.0,
                    1.0,
                    0.0
                ],
                [
                    0.0,
                    1.0,
                    0.0
                ],
                [
                    0.0,
                    2.0,
                    0.0
                ],
                [
                    0.0,
                    2.0,
                    0.0
                ],
                [
                    0.0,
                    4.0,
                    0.0
                ],
                [
                    0.0,
                    4.0,
                    0.0
                ],
                [
                    0.0,
                    8.0,
                    0.0
                ],
                [
                    0.0,
                    8.0,
                    0.0
                ],
                [
                    0.0,
                    16.0,
                    0.0
                ],
                [
                    0.0,
                    16.0,
                    0.0
                ],
                [
                    0.0,
                    32.0,
                    0.0
                ],
                [
                    0.0,
                    32.0,
                    0.0
                ],
                [
                    0.0,
                    64.0,
                    0.0
                ],
                [
                    0.0,
                    64.0,
                    0.0
                ],
                [
                    0.0,
                    128.0,
                    0.0
                ],
                [
                    0.0,
                    128.0,
                    0.0
                ],
                [
                    -128.0,
                    0.0,
                    0.0
                ],
                [
                    -128.0,
                    0.0,
                    0.0
                ],
                [
                    -128.0,
                    64.0,
                    0.0
                ],
                [
                    -128.0,
                    64.0,
                    0.0
                ],
                [
                    -128.0,
                    128.0,
                    0.0
                ],
                [
                    -128.0,
                    128.0,
                    0.0
                ],
                [
                    -128.0,
                    192.0,
                    0.0
                ],
                [
                    -128.0,
                    192.0,
                    0.0
                ],
                [
                    -128.0,
                    256.0,
                    0.0
                ],
                [
                    -128.0,
                    256.0,
                    0.0
                ],
                [
                    -128.0,
                    320.0,
                    0.0
                ],
                [
                    -128.0,
                    320.0,
                    0.0
                ],
                [
                    -128.0,
                    384.0,
                    0.0
                ],
                [
                    -128.0,
                    384.0,
                    0.0
                ],
                [
                    -0.0,
                    -0.0,
                    0.0
                ],
                [
                    -0.0,
                    -0.0,
                    0.0
                ],
                [
                    0.0,
                    -51.2,
                    0.0
                ],
                [
                    0.0,
                    -51.2,
                    0.0
                ],
                [
                    0.0,
                    -102.4,
                    0.0
                ],
                [
                    0.0,
                    -102.4,
                    0.0
                ],
                [
                    0.0,
                    -153.60000000000002,
                    0.0
                ],
                [
                    0.0,
                    -153.60000000000002,
                    0.0
                ],
                [
                    0.0,
                    -204.8,
                    0.0
                ],
                [
                    0.0,
                    -204.8,
                    0.0
                ],
                [
                    0.0,
                    -256.0,
                    0.0
                ],
                [
                    0.0,
                    -256.0,
                    0.0
                ],
                [
                    0.0,
                    -307.20000000000005,
                    0.0
                ],
                [
                    0.0,
                    -307.20000000000005,
                    0.0
                ],
                [
                    0.0,
                    -358.40000000000003,
                    0.0
                ],
                [
                    0.0,
                    -358.40000000000003,
                    0.0
                ],
                [
                    358.40000000000003,
                    51.2,
                    0.0
                ],
                [
                    358.40000000000003,
                    51.2,
                    0.0
                ],
                [
                    358.40000000000003,
                    102.4,
                    0.0
                ],
                [
                    358.40000000000003,
                    102.4,
                    0.0
                ],
                [
                    358.40000000000003,
                    153.60000000000002,
                    0.0
                ],
                [
                    358.40000000000003,
                    153.60000000000002,
                    0.0
                ],
                [
                    358.40000000000003,
                    204.8,
                    0.0
                ],
                [
                    358.40000000000003,
                    204.8,
                    0.0
                ],
                [
                    358.40000000000003,
                    256.0,
                    0.0
                ],
                [
                    358.40000000000003,
                    256.0,
                    0.0
                ],
                [
                    -0.0,
                    -0.0,
                    0.0
                ],
                [
                    -0.0,
                    -0.0,
                    0.0
                ],
                [
                    -0.0,
                    -0.0,
                    0.0
                ]
            ]
        ],
        "pixels_per_step": 0.9985007890335177,
        "pixels_per_step_vector": [
            0.6380831513598781,
            -0.7680193471854757
        ],
        "stage_axis": "X",
        "stage_direction": [
            0.7693135885883988,
            0.6388713504401646,
            0.0
        ]
    },
    "linear_calibration_Y": {
        "backlash": 0,
        "backlash_corrected_moves": [
            [
                [
                    -358.40000000000003,
                    -256.0,
                    0.0
                ]
            ],
            [
                [
                    -256.0,
                    358.0
                ]
            ],
            [
                1715723863.487238
            ]
        ],
        "exponential_moves": [
            [
                [
                    -0.0,
                    -0.0,
                    0.0
                ],
                [
                    -0.0,
                    -1.0,
                    0.0
                ],
                [
                    -0.0,
                    -2.0,
                    0.0
                ],
                [
                    -0.0,
                    -4.0,
                    0.0
                ],
                [
                    -0.0,
                    -8.0,
                    0.0
                ],
                [
                    -0.0,
                    -16.0,
                    0.0
                ],
                [
                    -0.0,
                    -32.0,
                    0.0
                ],
                [
                    -0.0,
                    -64.0,
                    0.0
                ],
                [
                    -0.0,
                    -128.0,
                    0.0
                ],
                [
                    128.0,
                    -0.0,
                    0.0
                ],
                [
                    128.0,
                    -64.0,
                    0.0
                ],
                [
                    128.0,
                    -128.0,
                    0.0
                ],
                [
                    128.0,
                    -192.0,
                    0.0
                ],
                [
                    128.0,
                    -256.0,
                    0.0
                ],
                [
                    128.0,
                    -320.0,
                    0.0
                ],
                [
                    128.0,
                    -384.0,
                    0.0
                ]
            ],
            [
                [
                    0.0,
                    0.0
                ],
                [
                    -1.0,
                    0.0
                ],
                [
                    -2.0,
                    0.0
                ],
                [
                    -4.0,
                    0.0
                ],
                [
                    -8.0,
                    0.0
                ],
                [
                    -16.0,
                    0.0
                ],
                [
                    -32.0,
                    0.0
                ],
                [
                    -64.0,
                    0.0
                ],
                [
                    -128.0,
                    0.0
                ],
                [
                    0.0,
                    -128.0
                ],
                [
                    -64.0,
                    -128.0
                ],
                [
                    -128.0,
                    -128.0
                ],
                [
                    -192.0,
                    -128.0
                ],
                [
                    -256.0,
                    -128.0
                ],
                [
                    -320.0,
                    -128.0
                ],
                [
                    -384.0,
                    -128.0
                ]
            ],
            [
                1715723847.839486,
                1715723848.34577,
                1715723848.844447,
                1715723849.4063418,
                1715723849.925746,
                1715723850.482539,
                1715723850.998154,
                1715723851.502264,
                1715723852.016002,
                1715723852.5277922,
                1715723853.0923798,
                1715723853.613364,
                1715723854.127506,
                1715723854.649379,
                1715723855.187681,
                1715723855.703767
            ]
        ],
        "fractional_error": 0.0004374971801513109,
        "image_direction": [
            0.7691724990311398,
            -0.6390412089483677
        ],
        "linear_moves": [
            [
                [
                    0.0,
                    0.0,
                    0.0
                ],
                [
                    -0.0,
                    51.2,
                    0.0
                ],
                [
                    -0.0,
                    102.4,
                    0.0
                ],
                [
                    -0.0,
                    153.60000000000002,
                    0.0
                ],
                [
                    -0.0,
                    204.8,
                    0.0
                ],
                [
                    -0.0,
                    256.0,
                    0.0
                ],
                [
                    -0.0,
                    307.20000000000005,
                    0.0
                ],
                [
                    -0.0,
                    358.40000000000003,
                    0.0
                ],
                [
                    -0.0,
                    358.40000000000003,
                    0.0
                ],
                [
                    -358.40000000000003,
                    -51.2,
                    0.0
                ],
                [
                    -358.40000000000003,
                    -102.4,
                    0.0
                ],
                [
                    -358.40000000000003,
                    -153.60000000000002,
                    0.0
                ],
                [
                    -358.40000000000003,
                    -204.8,
                    0.0
                ],
                [
                    -358.40000000000003,
                    -256.0,
                    0.0
                ]
            ],
            [
                [
                    0.0,
                    0.0
                ],
                [
                    51.00000000000001,
                    0.0
                ],
                [
                    102.0,
                    0.0
                ],
                [
                    153.0,
                    0.0
                ],
                [
                    204.0,
                    0.0
                ],
                [
                    256.0,
                    0.0
                ],
                [
                    307.0,
                    0.0
                ],
                [
                    358.0,
                    0.0
                ],
                [
                    358.0,
                    0.0
                ],
                [
                    -51.0,
                    358.0
                ],
                [
                    -102.0,
                    358.0
                ],
                [
                    -153.0,
                    358.0
                ],
                [
                    -204.0,
                    358.0
                ],
                [
                    -256.0,
                    358.0
                ]
            ],
            [
                1715723856.234349,
                1715723856.728632,
                1715723857.24445,
                1715723857.8021,
                1715723858.306802,
                1715723858.877305,
                1715723859.348185,
                1715723859.847467,
                1715723860.288682,
                1715723860.8270872,
                1715723861.3625221,
                1715723861.9242601,
                1715723862.437509,
                1715723863.101324
            ]
        ],
        "move_history": [
            [
                1715723847.8397598,
                1715723847.987378,
                1715723848.357431,
                1715723848.490589,
                1715723848.854389,
                1715723848.980169,
                1715723849.417774,
                1715723849.547612,
                1715723849.937641,
                1715723850.083545,
                1715723850.492316,
                1715723850.622345,
                1715723851.008476,
                1715723851.138004,
                1715723851.5129988,
                1715723851.63789,
                1715723852.026932,
                1715723852.153915,
                1715723852.537602,
                1715723852.66831,
                1715723853.103026,
                1715723853.228721,
                1715723853.623706,
                1715723853.751078,
                1715723854.141674,
                1715723854.267529,
                1715723854.6595001,
                1715723854.790486,
                1715723855.1975439,
                1715723855.325342,
                1715723855.713641,
                1715723855.841043,
                1715723856.23459,
                1715723856.362043,
                1715723856.729223,
                1715723856.855392,
                1715723857.244917,
                1715723857.3731258,
                1715723857.802668,
                1715723857.9296482,
                1715723858.3072808,
                1715723858.4310012,
                1715723858.87796,
                1715723859.0082529,
                1715723859.3486981,
                1715723859.477102,
                1715723860.2890508,
                1715723860.427325,
                1715723860.8275342,
                1715723860.9575732,
                1715723861.363192,
                1715723861.4938471,
                1715723861.924556,
                1715723862.051167,
                1715723862.437969,
                1715723862.56613,
                1715723863.487346,
                1715723863.611685,
                1715723863.611687,
                1715723863.73721
            ],
            [
                [
                    -0.0,
                    -0.0,
                    0.0
                ],
                [
                    1.0,
                    0.0,
                    0.0
                ],
                [
                    1.0,
                    0.0,
                    0.0
                ],
                [
                    2.0,
                    0.0,
                    0.0
                ],
                [
                    2.0,
                    0.0,
                    0.0
                ],
                [
                    4.0,
                    0.0,
                    0.0
                ],
                [
                    4.0,
                    0.0,
                    0.0
                ],
                [
                    8.0,
                    0.0,
                    0.0
                ],
                [
                    8.0,
                    0.0,
                    0.0
                ],
                [
                    16.0,
                    0.0,
                    0.0
                ],
                [
                    16.0,
                    0.0,
                    0.0
                ],
                [
                    32.0,
                    0.0,
                    0.0
                ],
                [
                    32.0,
                    0.0,
                    0.0
                ],
                [
                    64.0,
                    0.0,
                    0.0
                ],
                [
                    64.0,
                    0.0,
                    0.0
                ],
                [
                    128.0,
                    0.0,
                    0.0
                ],
                [
                    128.0,
                    0.0,
                    0.0
                ],
                [
                    0.0,
                    -128.0,
                    0.0
                ],
                [
                    0.0,
                    -128.0,
                    0.0
                ],
                [
                    64.0,
                    -128.0,
                    0.0
                ],
                [
                    64.0,
                    -128.0,
                    0.0
                ],
                [
                    128.0,
                    -128.0,
                    0.0
                ],
                [
                    128.0,
                    -128.0,
                    0.0
                ],
                [
                    192.0,
                    -128.0,
                    0.0
                ],
                [
                    192.0,
                    -128.0,
                    0.0
                ],
                [
                    256.0,
                    -128.0,
                    0.0
                ],
                [
                    256.0,
                    -128.0,
                    0.0
                ],
                [
                    320.0,
                    -128.0,
                    0.0
                ],
                [
                    320.0,
                    -128.0,
                    0.0
                ],
                [
                    384.0,
                    -128.0,
                    0.0
                ],
                [
                    384.0,
                    -128.0,
                    0.0
                ],
                [
                    -0.0,
                    -0.0,
                    0.0
                ],
                [
                    -0.0,
                    -0.0,
                    0.0
                ],
                [
                    -51.2,
                    0.0,
                    0.0
                ],
                [
                    -51.2,
                    0.0,
                    0.0
                ],
                [
                    -102.4,
                    0.0,
                    0.0
                ],
                [
                    -102.4,
                    0.0,
                    0.0
                ],
                [
                    -153.60000000000002,
                    0.0,
                    0.0
                ],
                [
                    -153.60000000000002,
                    0.0,
                    0.0
                ],
                [
                    -204.8,
                    0.0,
                    0.0
                ],
                [
                    -204.8,
                    0.0,
                    0.0
                ],
                [
                    -256.0,
                    0.0,
                    0.0
                ],
                [
                    -256.0,
                    0.0,
                    0.0
                ],
                [
                    -307.20000000000005,
                    0.0,
                    0.0
                ],
                [
                    -307.20000000000005,
                    0.0,
                    0.0
                ],
                [
                    -358.40000000000003,
                    0.0,
                    0.0
                ],
                [
                    -358.40000000000003,
                    0.0,
                    0.0
                ],
                [
                    51.2,
                    358.40000000000003,
                    0.0
                ],
                [
                    51.2,
                    358.40000000000003,
                    0.0
                ],
                [
                    102.4,
                    358.40000000000003,
                    0.0
                ],
                [
                    102.4,
                    358.40000000000003,
                    0.0
                ],
                [
                    153.60000000000002,
                    358.40000000000003,
                    0.0
                ],
                [
                    153.60000000000002,
                    358.40000000000003,
                    0.0
                ],
                [
                    204.8,
                    358.40000000000003,
                    0.0
                ],
                [
                    204.8,
                    358.40000000000003,
                    0.0
                ],
                [
                    256.0,
                    358.40000000000003,
                    0.0
                ],
                [
                    256.0,
                    358.40000000000003,
                    0.0
                ],
                [
                    -0.0,
                    -0.0,
                    0.0
                ],
                [
                    -0.0,
                    -0.0,
                    0.0
                ],
                [
                    -0.0,
                    -0.0,
                    0.0
                ]
            ]
        ],
        "pixels_per_step": -0.9985007890335177,
        "pixels_per_step_vector": [
            -0.7680193471854757,
            0.6380831513598781
        ],
        "stage_axis": "Y",
        "stage_direction": [
            -0.6388713504401646,
            -0.7693135885883988,
            0.0
        ]
    }
}